vintagify/__init__.py
vintagify/api.py
vintagify/batch_preprocess.py
vintagify/bind_dataset.py
vintagify/discriminator.py
vintagify/generator.py
vintagify/inference.py
vintagify/optimize_loss.py
vintagify/preprocess.py
vintagify/train.py
vintagify/resources/G_A2B_epoch33.pth
vintagify-0.1.2.dist-info/licenses/LICENSE
vintagify-0.1.2.dist-info/METADATA
vintagify-0.1.2.dist-info/WHEEL
vintagify-0.1.2.dist-info/top_level.txt
vintagify-0.1.2.dist-info/RECORD
